{"fields":{"name":"tribe_list115","state":"tribe_list116","country":"tribe_list117"},"labels":{"tribe_list115":{"table_name":"dle20u3275018691","serial_number":"10","field_type":null,"filed_length":null,"field_label":"Name","display_field_label":"","form_field":"text","form_field_options":"","required_field":"yes","data":[],"database_objects":"","attributes":"","class":"","default_appearance_in_table_fields":"show","display_position":"display-in-table-row","acceptable_files_format":"","field_id":"tribe_list115","group":"","id":"dds20u3275023161","serial_num":"115","created_by":"35991362173","modification_date":"1684414217","creation_date":"1684414217","modified_by":"35991362173","text":"Name","field_key":"tribe_list115","table":"tribe_list","field_identifier":"name"},"tribe_list116":{"table_name":"dle20u3275018691","serial_number":"20","field_type":null,"filed_length":null,"field_label":"State","display_field_label":"","form_field":"text","form_field_options":"","required_field":"no","data":[],"database_objects":"","attributes":"","class":"","default_appearance_in_table_fields":"show","display_position":"display-in-table-row","acceptable_files_format":"","field_id":"tribe_list116","group":"","id":"dds20u3275023261","serial_num":"116","created_by":"35991362173","modification_date":"1684414249","creation_date":"1684414227","modified_by":"35991362173","text":"State","field_key":"tribe_list116","table":"tribe_list","field_identifier":"state"},"tribe_list117":{"table_name":"dle20u3275018691","serial_number":"30","field_type":null,"filed_length":null,"field_label":"Country","display_field_label":"","form_field":"text","form_field_options":"","required_field":"no","data":[],"database_objects":"","attributes":"","class":"","default_appearance_in_table_fields":"show","display_position":"display-in-table-row","acceptable_files_format":"","field_id":"tribe_list117","group":"","id":"dds20u3275023391","serial_num":"117","created_by":"35991362173","modification_date":"1684414240","creation_date":"1684414240","modified_by":"35991362173","text":"Country","field_key":"tribe_list117","table":"tribe_list","field_identifier":"country"}}}